[
    {
        "تفتح عينك وتبص على الساعة… وتقول: لسه خمس دقايق.":"تفتح عينيك وتفتكر إنك ناسي تحل الشيت… وتقفل عينك تاني.",
        "هو أنا في الكلية ولا في سوق الجمعة؟":"فين الكافيتيريا؟ القهوة أهم من المحاضرة.",
        "ده المدرج ولا محطة قطار؟ الناس كلها قاعدة ليه كأنهم مستنيين حاجة كبيرة؟":"أقعد قدام عشان أبان مهتم ولا ورا عشان أهرب؟",
        "وأخيرًا! الحرية... بس لمدة كام ساعة.":"السرير، فينك بقى؟"
    },
    {
        "تفتح عينك وتبص على الساعة… وتقول: لسه خمس دقايق.":"تسمع صوت المنبه… وتقرر تتجاهله كأن الموضوع مش ليك.",
        "هو أنا في الكلية ولا في سوق الجمعة؟":"ده أنا لو فضلت تايه كده مش هلاقي المدرج أبدا.",
        "ده المدرج ولا محطة قطار؟ الناس كلها قاعدة ليه كأنهم مستنيين حاجة كبيرة؟":"الكرسي ده صلب كده ليه؟ ده بيساعد على التركيز ولا على الألم؟",
        "وأخيرًا! الحرية... بس لمدة كام ساعة.":"أنا داخل البيت زي البطل اللي راجع من معركة."
    },
    {
        "تفتح عينك وتبص على الساعة… وتقول: لسه خمس دقايق.":"أفتح عيني وأحاول أفهم أنا فين… الصبح ولا لسه بليل؟",
        "هو أنا في الكلية ولا في سوق الجمعة؟":"هو أنا هافضل أدور على المدرج لحد ما السنة تخلص؟",
        "ده المدرج ولا محطة قطار؟ الناس كلها قاعدة ليه كأنهم مستنيين حاجة كبيرة؟":"أقعد جنب حد شكله مذاكر ولا حد شكله ضايع زيي؟",
        "وأخيرًا! الحرية... بس لمدة كام ساعة.":"يا ترى المذاكرة هتبدأ إمتى؟ يمكن بعد النوم... يمكن مش هتبدأ أصلاً."
    },
    {
        "تفتح عينك وتبص على الساعة… وتقول: لسه خمس دقايق.":"تقفل المنبه وتقول: هو لازم أروح الجامعة؟",
        "هو أنا في الكلية ولا في سوق الجمعة؟":"أول يوم وعديت بوابة الكلية، أنا كده بطل رسمي.",
        "ده المدرج ولا محطة قطار؟ الناس كلها قاعدة ليه كأنهم مستنيين حاجة كبيرة؟":"ده أنا دخلت متأخر والدكتور بدأ؟ هعمل نفسي بكتب حاجات مهمة.",
        "وأخيرًا! الحرية... بس لمدة كام ساعة.":"بطني بتقول لي: 'عايز أكل دلوقتي حالًا!'"
    },
    {
        "تفتح عينك وتبص على الساعة… وتقول: لسه خمس دقايق.":"تفتح عينك وتركب الفيلم في دماغك إنك صحيت متأخر، وتجري من غير ما تفكر.",
        "هو أنا في الكلية ولا في سوق الجمعة؟":"إيه الزحمة دي؟ هو إحنا في حفلة ولا إيه؟",
        "ده المدرج ولا محطة قطار؟ الناس كلها قاعدة ليه كأنهم مستنيين حاجة كبيرة؟":"هو إيه اللي خلاني أقعد هنا؟ أنا كان لازم أجيب مخدة معايا.",
        "وأخيرًا! الحرية... بس لمدة كام ساعة.":"هاكل إيه؟ هم أصلاً في أكل؟"
    },
    {
        "تفتح عينك وتبص على الساعة… وتقول: لسه خمس دقايق.":"تصحى مفزوع كأنك هربان من مصيبة… وتلاقي لسه بدري.\nتبص على هدومك اللي محضّرها من الأسبوع اللي فات… وتلبس حاجة تانية خالص.\"",
        "هو أنا في الكلية ولا في سوق الجمعة؟":"أول ما دخلت حسيت إني في مكان غريب.. حد يدلني عالدنيا.",
        "ده المدرج ولا محطة قطار؟ الناس كلها قاعدة ليه كأنهم مستنيين حاجة كبيرة؟":"المدرج كله نايم! أروح أنام أنا كمان ولا أصحصح عشان أبان شاطر؟",
        "وأخيرًا! الحرية... بس لمدة كام ساعة.":"بعد كل ده، أنا محتاج وجبة كاملة... وشيكولاته بعدها!"
    },
    {
        "تفتح عينك وتبص على الساعة… وتقول: لسه خمس دقايق.":"تبص على دولابك وتقول: ‘أي حاجة هتنفع، أصلًا كله شكل بعضه.’",
        "هو أنا في الكلية ولا في سوق الجمعة؟":"أول ما تدخل الجامعة هتحس إنك في فيلم أكشن:",
        "ده المدرج ولا محطة قطار؟ الناس كلها قاعدة ليه كأنهم مستنيين حاجة كبيرة؟":"إزاي أخرج من هنا لو المحاضرة طولت؟ مفيش مخرج طوارئ؟",
        "وأخيرًا! الحرية... بس لمدة كام ساعة.":"هو في أكل هيصحيني من الليلة دي ولا ننام وخلاص؟"
    },
    {
        "تفتح عينك وتبص على الساعة… وتقول: لسه خمس دقايق.":"تقعد تفكر: ألبس كاجوال ولا رسمي؟ بس في الآخر تلبس أي حاجة تلاقيها.",
        "هو أنا في الكلية ولا في سوق الجمعة؟":"هو ده المدرج ولا قاعة أفراح؟",
        "ده المدرج ولا محطة قطار؟ الناس كلها قاعدة ليه كأنهم مستنيين حاجة كبيرة؟":"اللي جابني هنا كان بيكرهني... ده أكيد مش مكان للدراسة!",
        "وأخيرًا! الحرية... بس لمدة كام ساعة.":"أذاكر دلوقتي ولا أستنى شوية؟ شوية يعني يومين."
    },
    {
        "تفتح عينك وتبص على الساعة… وتقول: لسه خمس دقايق.":"تفضل تجرّب لبس وتحس نفسك رايح فرح، مش الجامعة!",
        "هو أنا في الكلية ولا في سوق الجمعة؟":"فين أقرب مكان للقهوة؟ أنا مش هعرف أركز كده.",
        "ده المدرج ولا محطة قطار؟ الناس كلها قاعدة ليه كأنهم مستنيين حاجة كبيرة؟":"ليه فيه ناس لابسة كاجوال وأنا جاي كأني رايح اجتماع رسمي؟",
        "وأخيرًا! الحرية... بس لمدة كام ساعة.":"مش يمكن لو نمت بدري دماغي تبقى فريش بكرة؟"
    },
    {
        "تفتح عينك وتبص على الساعة… وتقول: لسه خمس دقايق.":"تفتح الدولاب وتختار أول حاجة تطلع… لأنك أصلًا متأخر.",
        "هو أنا في الكلية ولا في سوق الجمعة؟":"ده أنا تايه من أول دقيقة، ده لسه المشوار طويل.",
        "ده المدرج ولا محطة قطار؟ الناس كلها قاعدة ليه كأنهم مستنيين حاجة كبيرة؟":"الدكتور ده جاي يشرح ولا جاي يحقق معانا؟",
        "وأخيرًا! الحرية... بس لمدة كام ساعة.":"الكتب في الشنطة، والشنطة على الأرض... والهمة في الزيرو."
    },
    {
        "تفتح عينك وتبص على الساعة… وتقول: لسه خمس دقايق.":"تقعد تختار هدوم لمدة نص ساعة، وفي الآخر تلبس نفس الجاكت اللي لابسه من سنة.",
        "هو أنا في الكلية ولا في سوق الجمعة؟":"شكل الكلية دي محتاجة خريطة عشان ألاقي أي حاجة.",
        "ده المدرج ولا محطة قطار؟ الناس كلها قاعدة ليه كأنهم مستنيين حاجة كبيرة؟":"هو ليه الدكتور دا ماسك الكتاب كأنه دليل اتهام؟",
        "وأخيرًا! الحرية... بس لمدة كام ساعة.":"أنا عارف إن المذاكرة مهمة، بس النوم برضه مهم!"
    },
    {
        "تفتح عينك وتبص على الساعة… وتقول: لسه خمس دقايق.":"تقرر تلبس حاجة بسيطة… وتخرج في الآخر لابس زي رايح حفلة تخرج.",
        "هو أنا في الكلية ولا في سوق الجمعة؟":"الموضوع بدأ يعدي مني، حد يدلني عالمدرج بقى.",
        "ده المدرج ولا محطة قطار؟ الناس كلها قاعدة ليه كأنهم مستنيين حاجة كبيرة؟":"أعمل نفسي بكتب من أول دقيقة ولا أراقب اللي حواليّ؟",
        "وأخيرًا! الحرية... بس لمدة كام ساعة.":"طب أقلب في الكتاب شوية؟ لا، مش للدرجة دي!"
    },
    {
        "تفتح عينك وتبص على الساعة… وتقول: لسه خمس دقايق.":"تروح الحمام وأنت نايم نص نومة ولسه مش شايف الطريق.",
        "هو أنا في الكلية ولا في سوق الجمعة؟":"يا ريتني جبت جي بي إس، الكلية دي كبيرة أوي.",
        "ده المدرج ولا محطة قطار؟ الناس كلها قاعدة ليه كأنهم مستنيين حاجة كبيرة؟":"الدكتور شكله مش جاي على خير، ده شكله طول النهار بيدعي علينا.",
        "وأخيرًا! الحرية... بس لمدة كام ساعة.":"يا نهار، ده لسه فيه واجب لازم يتسلم بكرة!"
    },
    {
        "تفتح عينك وتبص على الساعة… وتقول: لسه خمس دقايق.":"تدخل الحمام، وبدل ما تغسل وشك… تقف وتبص في المراية تحاول تفتكر اسمك.",
        "هو أنا في الكلية ولا في سوق الجمعة؟":"أول ما تدخل الجامعة هتحس إنك تايه في مدينة تانية:",
        "ده المدرج ولا محطة قطار؟ الناس كلها قاعدة ليه كأنهم مستنيين حاجة كبيرة؟":"هو بيشرح بالراحة كده ليه؟ ده عنده محاضرات كتير ولا إيه؟",
        "وأخيرًا! الحرية... بس لمدة كام ساعة.":"الواجب ده لازم أخلصه دلوقتي ولا أقدر أستناه لآخر لحظة؟"
    },
    {
        "تفتح عينك وتبص على الساعة… وتقول: لسه خمس دقايق.":"تغسل وشك وتفضل تسأل نفسك: ‘هو أنا محتاج أكون هنا دلوقتي؟’",
        "هو أنا في الكلية ولا في سوق الجمعة؟":"ده أنا هفضل تايه لآخر السنة.",
        "ده المدرج ولا محطة قطار؟ الناس كلها قاعدة ليه كأنهم مستنيين حاجة كبيرة؟":"الدكتور بيبص لي كأن عنده أسئلة صعبة وأنا مش عارف حتى المادة اسمها إيه.",
        "وأخيرًا! الحرية... بس لمدة كام ساعة.":"الواجب شكله بيقول لي: 'مش هترتاح النهارده'."
    },
    {
        "تفتح عينك وتبص على الساعة… وتقول: لسه خمس دقايق.":"تفكر إنك تعمل فطار سريع، وبعدين تقرر تشرب مية وخلاص.",
        "هو أنا في الكلية ولا في سوق الجمعة؟":"فين الناس اللي قالوا الجامعة سهلة؟",
        "ده المدرج ولا محطة قطار؟ الناس كلها قاعدة ليه كأنهم مستنيين حاجة كبيرة؟":"أبدأ أكتب حاجات مش فاهمها ولا أنام وأصحى على التصفيق؟",
        "وأخيرًا! الحرية... بس لمدة كام ساعة.":"هو الواجب ده مطلوب مني أنا ولا ده فيلم رعب؟"
    },
    {
        "تفتح عينك وتبص على الساعة… وتقول: لسه خمس دقايق.":"تفتح التلاجة وتلاقي مفيش غير كوباية شاي باردة… تقرر تشربها وتكمل.",
        "هو أنا في الكلية ولا في سوق الجمعة؟":"طب أنا أروح المحاضرة ولا أبدأ بالكافيتيريا؟",
        "ده المدرج ولا محطة قطار؟ الناس كلها قاعدة ليه كأنهم مستنيين حاجة كبيرة؟":"إزاي الناس اللي جنبي بتكتب بسرعة كده؟ ده أنا لسه بفتح القلم!",
        "وأخيرًا! الحرية... بس لمدة كام ساعة.":"أبدأ أكتب حل الشيت؟ ولا أبدأ أحاول أفهم أصلاً إيه المطلوب؟"
    },
    {
        "تفتح عينك وتبص على الساعة… وتقول: لسه خمس دقايق.":"تقرر تفطر بيض، بس أول ما تبدأ، تفتكر إنك أصلًا مش فاضي للبيض.",
        "هو أنا في الكلية ولا في سوق الجمعة؟":"الواحد داخل هنا بآمال وأحلام وخرج بتوهان.",
        "ده المدرج ولا محطة قطار؟ الناس كلها قاعدة ليه كأنهم مستنيين حاجة كبيرة؟":"أعمل نفسي مهتم وأهز راسي كل شوية؟",
        "وأخيرًا! الحرية... بس لمدة كام ساعة.":"وأول ما تقرر تأخذ استراحة وتفتح السوشيال ميديا:\"خمس دقايق على فيسبوك... واتنين على إنستجرام... وهب الساعة بقت 11 بالليل.\""
    },
    {
        "تفتح عينك وتبص على الساعة… وتقول: لسه خمس دقايق.":"تفكر في تحضير فطار، بس تفتكر إن الكافيتيريا هي الحل.",
        "هو أنا في الكلية ولا في سوق الجمعة؟":"هو أنا جيت أدرس ولا أتوه؟",
        "ده المدرج ولا محطة قطار؟ الناس كلها قاعدة ليه كأنهم مستنيين حاجة كبيرة؟":"الدكتور بيشرح حاجة شكلها من كوكب تاني، وأنا المفروض أفهم؟",
        "وأخيرًا! الحرية... بس لمدة كام ساعة.":"طب أنا كنت هأذاكر... بس لازم أبقى مطلع على آخر الأخبار! نفتح فيس بقا"
    },
    {
        "تفتح عينك وتبص على الساعة… وتقول: لسه خمس دقايق.":"تطلع سندوتش من الثلاجة متحمس، وفي الآخر تاخده معاك تاكله في الطريق.",
        "هو أنا في الكلية ولا في سوق الجمعة؟":"أول يوم وكل ده زحمة.. أمال الامتحانات هتبقى إيه؟",
        "ده المدرج ولا محطة قطار؟ الناس كلها قاعدة ليه كأنهم مستنيين حاجة كبيرة؟":"لو طلب مني أجاوب دلوقتي، أقوله أنا كنت في المحاضرة الغلط؟",
        "وأخيرًا! الحرية... بس لمدة كام ساعة.":"الناس كلها بتذاكر، وأنا اللي تايه في الميمز؟"
    },
    {
        "تفتح عينك وتبص على الساعة… وتقول: لسه خمس دقايق.":"تشرب شاي على الريق، وتفتكر إنك لسه مطحون من الامتحانات اللي فاتت.",
        "هو أنا في الكلية ولا في سوق الجمعة؟":"حاسس إني في مشهد من أفلام الأكشن، كل الناس بتجري.",
        "ده المدرج ولا محطة قطار؟ الناس كلها قاعدة ليه كأنهم مستنيين حاجة كبيرة؟":"يا ترى فيه تسجيل للمحاضرة دي عشان أفهمها بعدين؟",
        "وأخيرًا! الحرية... بس لمدة كام ساعة.":"يا رب أكون ضيعت وقتي على حاجة مفيدة! أكيد الميمز دي بتعلمني حاجة!"
    },
    {
        "تفتح عينك وتبص على الساعة… وتقول: لسه خمس دقايق.":"تلبس الجاكت وأنت مش عارف الجو بره عامل إزاي… وفي الآخر تكتشف إنك لابس غلط.",
        "هو أنا في الكلية ولا في سوق الجمعة؟":"ده أنا لو فضلت ألف يومين كمان مش هلاقي المدرج.",
        "ده المدرج ولا محطة قطار؟ الناس كلها قاعدة ليه كأنهم مستنيين حاجة كبيرة؟":"وأول ما المحاضرة تخلص وتقوم:\"ده أنا مش قادر أقف من كتر القعدة! المدرج ده مصيدة.\"",
        "وأخيرًا! الحرية... بس لمدة كام ساعة.":"بس هو فين الوقت اللي كنت هأذاكر فيه؟"
    },
    {
        "تفتح عينك وتبص على الساعة… وتقول: لسه خمس دقايق.":"تحط كل حاجة في الشنطة ما عدا الحاجة اللي هتحتاجها فعلاً.",
        "هو أنا في الكلية ولا في سوق الجمعة؟":"يا ريتني جبت حذاء رياضي، الجامعة دي جيم مش كلية.",
        "ده المدرج ولا محطة قطار؟ الناس كلها قاعدة ليه كأنهم مستنيين حاجة كبيرة؟":"الحمد لله المحاضرة خلصت، أخيراً أتنفس!",
        "وأخيرًا! الحرية... بس لمدة كام ساعة.":"يوم طويل وعدى... والمذاكرة هتستنانا في الحلقة الجاية."
    },
    {
        "تفتح عينك وتبص على الساعة… وتقول: لسه خمس دقايق.":"تفضل تفتش في شنطتك على الكارنيه… وفي الآخر تلاقيه في جيبك من الأول.",
        "هو أنا في الكلية ولا في سوق الجمعة؟":"إحساس غريب إني في الجامعة.. ولسه مش لاقي المدرج.",
        "ده المدرج ولا محطة قطار؟ الناس كلها قاعدة ليه كأنهم مستنيين حاجة كبيرة؟":"وأول ما المحاضرة تخلص وتقوم:\"أخرج بسرعة قبل ما الدكتور يطلب واجب أو حاجة.\"",
        "وأخيرًا! الحرية... بس لمدة كام ساعة.":"أنا بطل فيلم هندي، كل يوم أقول هأذاكر، وبعدين..."
    },
    {
        "تفتح عينك وتبص على الساعة… وتقول: لسه خمس دقايق.":"تستعد للخروج، وتكتشف إنك نسيت المفتاح جوا البيت.",
        "هو أنا في الكلية ولا في سوق الجمعة؟":"أنا جيت أتعلم ولا أمارس رياضة الجري السريع؟",
        "ده المدرج ولا محطة قطار؟ الناس كلها قاعدة ليه كأنهم مستنيين حاجة كبيرة؟":"أقول لصاحبي: هنروح الكافيتيريا ولا نروح نذاكر؟ لا، الكافيتيريا أحسن.",
        "وأخيرًا! الحرية... بس لمدة كام ساعة.":"الحمد لله، يوم عدى، بس المشكلة إن فيه بكرة."
    },
    {
        "تفتح عينك وتبص على الساعة… وتقول: لسه خمس دقايق.":"تخرج وتفتكر إنك ناسي حاجة… بس مش عارف إيه بالضبط.",
        "هو أنا في الكلية ولا في سوق الجمعة؟":"حد يقولي هما ليه مش بيوزعوا خرايط مع كارنيه الجامعة؟",
        "ده المدرج ولا محطة قطار؟ الناس كلها قاعدة ليه كأنهم مستنيين حاجة كبيرة؟":"لو كل محاضرة كده، يبقى أنا هحتاج كرسي بعجلات عشان أقدر أتنقل.",
        "وأخيرًا! الحرية... بس لمدة كام ساعة.":"أخد قرار: هنام دلوقتي وأذاكر في الحلم."
    },
    {
        "تفتح عينك وتبص على الساعة… وتقول: لسه خمس دقايق.":"تحط كل حاجة في الشنطة وتفتكر إنك ناسي الكتاب الوحيد المهم.",
        "هو أنا في الكلية ولا في سوق الجمعة؟":"أول ما دخلت الجامعة حسيت إني في مدينة ملاهي.",
        "ده المدرج ولا محطة قطار؟ الناس كلها قاعدة ليه كأنهم مستنيين حاجة كبيرة؟":"أرفع إيدي ولا أخاف أبان إن مش فاهم حاجة؟",
        "وأخيرًا! الحرية... بس لمدة كام ساعة.":"أنا لسه عايش؟ يوم كامل في الجامعة ولسه على قيد الحياة؟ معجزة!"
    },
    {
        "تفتح عينك وتبص على الساعة… وتقول: لسه خمس دقايق.":"أول حاجة أعملها؟ أقفل المنبه وأرجع أنام… العشرين دقيقة اللي جايين دول أهم من المحاضرة.",
        "هو أنا في الكلية ولا في سوق الجمعة؟":"هو فيه GPS للمدرجات؟",
        "ده المدرج ولا محطة قطار؟ الناس كلها قاعدة ليه كأنهم مستنيين حاجة كبيرة؟":"طب لما أسأل، أعمل نفسي فاهم النص التاني ولا أسأل بجرأة؟",
        "وأخيرًا! الحرية... بس لمدة كام ساعة.":"الدنيا في الجامعة مش طبيعية... دي مش دراسة دي سباق ماراثون!"
    },
    {
        "تفتح عينك وتبص على الساعة… وتقول: لسه خمس دقايق.":"أصحى، أبص على الساعة وأحاول أحسب لو نمت خمس دقايق كمان هل هالحق؟",
        "هو أنا في الكلية ولا في سوق الجمعة؟":"كل اللي بشوفه ناس بتجري.. طب فين المدرج؟",
        "ده المدرج ولا محطة قطار؟ الناس كلها قاعدة ليه كأنهم مستنيين حاجة كبيرة؟":"أقول للدكتور: ممكن تعيد آخر 45 دقيقة؟ مش فاهم منها حاجة.",
        "وأخيرًا! الحرية... بس لمدة كام ساعة.":"النهارده عديت اليوم الأول، بس بكرة؟ هنحتاج خارطة طريق عشان نرجع تاني."
    },
    {
        "تفتح عينك وتبص على الساعة… وتقول: لسه خمس دقايق.":"أفتح الموبايل الأول أشوف الساعة كام… وبعدين أقفل المنبه اللي من مبارح لسه شغال.",
        "هو أنا في الكلية ولا في سوق الجمعة؟":"الجامعة دي عبارة عن دوامة، وأنا عايز أخرج منها.",
        "ده المدرج ولا محطة قطار؟ الناس كلها قاعدة ليه كأنهم مستنيين حاجة كبيرة؟":"لو سألت السؤال ده، الناس هتضحك عليا ولا هما برضو مش فاهمين زيي؟",
        "وأخيرًا! الحرية... بس لمدة كام ساعة.":"لما دخلت الجامعة كنت فاكرها مغامرة، طلعت برنامج تدريب على الصبر."
    },
    {
        "تفتح عينك وتبص على الساعة… وتقول: لسه خمس دقايق.":"أول ما أصحى، أفتح الموبايل وأدخل على إنستجرام… عشان أشوف مين صحى قبلي!",
        "هو أنا في الكلية ولا في سوق الجمعة؟":"هو المدرج ده في آخر الدنيا ولا إيه؟",
        "ده المدرج ولا محطة قطار؟ الناس كلها قاعدة ليه كأنهم مستنيين حاجة كبيرة؟":"أنا هعمل نفسي متابع المحاضرة وأسيب الأسئلة للأسبوع الجاي.",
        "وأخيرًا! الحرية... بس لمدة كام ساعة.":"أهلي: 'إيه الأخبار؟' أنا: 'تجربة حياتية جديدة في الصبر والتعايش مع المعاناة.'"
    },
    {
        "تفتح عينك وتبص على الساعة… وتقول: لسه خمس دقايق.":"أسمع صوت المنبه وأحاول أفتكر ليه كنت حاطه من الأساس.",
        "هو أنا في الكلية ولا في سوق الجمعة؟":"كل ده علشان أحضر أول محاضرة؟ طب وبعد كده؟",
        "ده المدرج ولا محطة قطار؟ الناس كلها قاعدة ليه كأنهم مستنيين حاجة كبيرة؟":"أول ما تدخل المدرج وتلاقي مفيش مكان فاضي:\"أقف في النص وأعمل نفسي بدور على مكان، ولا أرجع وأهرب؟\"",
        "وأخيرًا! الحرية... بس لمدة كام ساعة.":"الدكتور النهارده كان بيشرح وكأنه بيحضر حلقة من مسلسل غموض."
    },
    {
        "تفتح عينك وتبص على الساعة… وتقول: لسه خمس دقايق.":"أول ما أصحى، أتحول لتمثال في السرير وأفضل كده 5 دقايق أحاول أفهم أنا فين.",
        "هو أنا في الكلية ولا في سوق الجمعة؟":"إحنا بندرس ولا بندور على الكنز المفقود؟",
        "ده المدرج ولا محطة قطار؟ الناس كلها قاعدة ليه كأنهم مستنيين حاجة كبيرة؟":"أول ما تدخل المدرج وتلاقي مفيش مكان فاضي:\"طب أنا لو فضلت واقف كده، الدكتور هيحسبني غايب؟\"",
        "وأخيرًا! الحرية... بس لمدة كام ساعة.":"أول ما تفكر إن فيه واجب يتسلم بكرة:\"يعني هو مش كفاية اليوم؟ واجب كمان؟ ده بيدوس على اللي باقي مني!\""
    },
    {
        "تفتح عينك وتبص على الساعة… وتقول: لسه خمس دقايق.":"أفتح عيني وأقفلها تاني كأني عملت إني صحيت خلاص.",
        "هو أنا في الكلية ولا في سوق الجمعة؟":"أول ما تشوف جدول المحاضرات هتقول:",
        "ده المدرج ولا محطة قطار؟ الناس كلها قاعدة ليه كأنهم مستنيين حاجة كبيرة؟":"يا نهار أبيض، هو كل الناس دي جت بدري ولا أنا اللي متأخر؟",
        "وأخيرًا! الحرية... بس لمدة كام ساعة.":"أول ما تفكر إن فيه واجب يتسلم بكرة:\"الواجب ده كأنه بيقولي: 'فاكر إنك خلصت؟ لأ، لسه بدري عليك!'\""
    },
    {
        "تفتح عينك وتبص على الساعة… وتقول: لسه خمس دقايق.":"أصحى، أبص على السقف وأفكر: هل فعلًا ضروري أروح الجامعة؟",
        "هو أنا في الكلية ولا في سوق الجمعة؟":"ده جدول ولا حكم مؤبد؟",
        "ده المدرج ولا محطة قطار؟ الناس كلها قاعدة ليه كأنهم مستنيين حاجة كبيرة؟":"يا ترى في كام واحد هنا نايم؟ عشان أقرر مصيري.",
        "وأخيرًا! الحرية... بس لمدة كام ساعة.":"أول ما تفكر إن فيه واجب يتسلم بكرة:\"أبدأ دلوقتي ولا أستنى حتى آخر 10 دقايق قبل التسليم؟\""
    },
    {
        "تفتح عينك وتبص على الساعة… وتقول: لسه خمس دقايق.":"أول ما أصحى، أفتكر إن فيه محاضرة الساعة 8… وأقرر إن مش هتفرق لو تأخرت.",
        "هو أنا في الكلية ولا في سوق الجمعة؟":"فين أيام الراحة؟ ده كله محاضرات!",
        "ده المدرج ولا محطة قطار؟ الناس كلها قاعدة ليه كأنهم مستنيين حاجة كبيرة؟":"لو فضلت واقف ممكن أبان أني ملتزم، وأطلع برة وأخلص.",
        "وأخيرًا! الحرية... بس لمدة كام ساعة.":"إزاي أشرح لأهلي إن فيه واجب محتاج معجزة إلهية عشان أخلصه؟"
    },
    {
        "تفتح عينك وتبص على الساعة… وتقول: لسه خمس دقايق.":"أفتح المنبه وأعمله snooze… وكأن المشكلة هتتحل كده.",
        "هو أنا في الكلية ولا في سوق الجمعة؟":"يوم الخميس كله محاضرات؟ أمال الفسحة إمتى؟",
        "ده المدرج ولا محطة قطار؟ الناس كلها قاعدة ليه كأنهم مستنيين حاجة كبيرة؟":"وأول ما تلاقي نفسك قاعد في الصف الأول:\"ده أنا جبت آخري، أول صف يعني العين عليا طول المحاضرة.\"",
        "وأخيرًا! الحرية... بس لمدة كام ساعة.":"أول ما تفكر إن فيه واجب يتسلم بكرة:\"لو الواجب ده كان ليه مشاعر، كان بكى على حالي!\""
    },
    {
        "تفتح عينك وتبص على الساعة… وتقول: لسه خمس دقايق.":"أقوم من السرير وأفضل أقول لنفسي: ‘يلا نبدأ اليوم’ وأنا عارف إني مش هتحرك.",
        "هو أنا في الكلية ولا في سوق الجمعة؟":"الجدول ده معمول عشان يدمر حياتي الاجتماعية.",
        "ده المدرج ولا محطة قطار؟ الناس كلها قاعدة ليه كأنهم مستنيين حاجة كبيرة؟":"أعمل نفسي بكتب حتى لو مش فاهم حاجة؟",
        "وأخيرًا! الحرية... بس لمدة كام ساعة.":"النوم ده دلوقتي نعمة من ربنا بعد اليوم ده."
    },
    {
        "تفتح عينك وتبص على الساعة… وتقول: لسه خمس دقايق.":"أول ما أصحى، أدور على النظارة… وبعدين أكتشف إن مفيش أمل أصحى.",
        "هو أنا في الكلية ولا في سوق الجمعة؟":"هو أنا هعيش في الكلية أكتر من البيت ولا إيه؟",
        "ده المدرج ولا محطة قطار؟ الناس كلها قاعدة ليه كأنهم مستنيين حاجة كبيرة؟":"الدكتور بيبص لي كأني مطلوب للتحقيق، الله يستر.",
        "وأخيرًا! الحرية... بس لمدة كام ساعة.":"هو أنا لو نمت هقوم بكرة أذاكر؟ ولا الموضوع ده مستحيل؟"
    },
    {
        "تفتح عينك وتبص على الساعة… وتقول: لسه خمس دقايق.":"أقوم أدور على الموبايل اللي وقع تحت السرير بسبب المنبه اللي بيرن.",
        "هو أنا في الكلية ولا في سوق الجمعة؟":"إيه ده! المدرج ده يجيب النوم من قبل ما الدكتور ييجي.",
        "ده المدرج ولا محطة قطار؟ الناس كلها قاعدة ليه كأنهم مستنيين حاجة كبيرة؟":"أنا كده اتحكم عليا بالقعدة دي طول السنة؟",
        "وأخيرًا! الحرية... بس لمدة كام ساعة.":"السرير بينادي عليا، بس المذاكرة واقفة بتقول: 'تنسانيش بقى'."
    },
    {
        "تفتح عينك وتبص على الساعة… وتقول: لسه خمس دقايق.":"أقوم وأقول: ‘ليه؟ ليه الصبح موجود أصلاً؟’",
        "هو أنا في الكلية ولا في سوق الجمعة؟":"أنا أقعد ورا عشان أهوب أو قدام عشان أركز؟",
        "ده المدرج ولا محطة قطار؟ الناس كلها قاعدة ليه كأنهم مستنيين حاجة كبيرة؟":"الكرسي ده مش مصمم للبني آدمين، ده للروبوتات اللي بتذاكر طول اليوم.",
        "وأخيرًا! الحرية... بس لمدة كام ساعة.":"لو نمت النهارده، يبقى بكرة يوم جديد من الكفاح... ولا يوم تاني من التوهان؟"
    },
    {
        "تفتح عينك وتبص على الساعة… وتقول: لسه خمس دقايق.":"أصحى مفزوع كأن فيه حريقة، وبعد كده أكتشف إن المنبه اللي صحاني.",
        "هو أنا في الكلية ولا في سوق الجمعة؟":"المدرج ده شكله أوسع من ملعب كرة.. ممكن أضيع فيه.",
        "ده المدرج ولا محطة قطار؟ الناس كلها قاعدة ليه كأنهم مستنيين حاجة كبيرة؟":"أعمل نفسي فاهم وأهز راسي وأكتب شوية خطوط؟",
        "وأخيرًا! الحرية... بس لمدة كام ساعة.":"هبدأ أنام دلوقتي... بس نتفق على حاجة: مفيش صحيان بدري!"
    },
    {
        "تفتح عينك وتبص على الساعة… وتقول: لسه خمس دقايق.":"أقوم من السرير وأول حاجة أفكر فيها: ‘إمتى الإجازة الجاية؟’",
        "هو أنا في الكلية ولا في سوق الجمعة؟":"أعمل نفسي مهتم من أول محاضرة ولا أسيبها براحتي؟",
        "ده المدرج ولا محطة قطار؟ الناس كلها قاعدة ليه كأنهم مستنيين حاجة كبيرة؟":"لو سألت حد جنبي، هيبص لي بنظرة: ‘إنت لسه مبتدئ ولا إيه؟’",
        "وأخيرًا! الحرية... بس لمدة كام ساعة.":"دكتور بكرة شكله مستنيني مع سؤال في أول 5 دقايق."
    },
    {
        "تفتح عينك وتبص على الساعة… وتقول: لسه خمس دقايق.":"أصحى وأقعد أكتب سيناريو في دماغي عن إن لو متأخرتش النهاردة، هتأخر بكره.",
        "هو أنا في الكلية ولا في سوق الجمعة؟":"إحساس غريب إني أخيراً لقيت المدرج بعد ما اتوّهت.",
        "ده المدرج ولا محطة قطار؟ الناس كلها قاعدة ليه كأنهم مستنيين حاجة كبيرة؟":"الدكتور بيشرح باللاتيني ولا إيه؟",
        "وأخيرًا! الحرية... بس لمدة كام ساعة.":"لو الدكتور بكرة سأل سؤال وأنا نايم، أجاوب بإيه؟ 'نمنا كويس الحمد لله؟'"
    },
    {
        "تفتح عينك وتبص على الساعة… وتقول: لسه خمس دقايق.":"أقوم وأقرر آخد يوم إجازة… وبعد كده أفتكر إن أول يوم دراسي مش محتاج إجازة.",
        "هو أنا في الكلية ولا في سوق الجمعة؟":"هو الدكتور ده بيبتسم ولا ده استدعاء للموت البطيء؟",
        "ده المدرج ولا محطة قطار؟ الناس كلها قاعدة ليه كأنهم مستنيين حاجة كبيرة؟":"يا جماعة، فين الترجمة؟ ده مش عربي ولا إنجليزي!",
        "وأخيرًا! الحرية... بس لمدة كام ساعة.":"الدكتور ده من النوع اللي مبيعذرش... أحسن لي أكون على قد التوقعات ومروحش بكره أصلاً."
    },
    {
        "تفتح عينك وتبص على الساعة… وتقول: لسه خمس دقايق.":"أصحى وأفكر أعمل قهوة، وبعدها أقرر إنها مش هتفيد وأنا أصلاً نايم.",
        "هو أنا في الكلية ولا في سوق الجمعة؟":"شكله مش جاي هزار.. هو أنا هعدي ولا لأ؟",
        "ده المدرج ولا محطة قطار؟ الناس كلها قاعدة ليه كأنهم مستنيين حاجة كبيرة؟":"وأول ما تلاقي المحاضرة عدت وفضل فيها ربع ساعة:\"لو خرجت دلوقتي هيلحظوا؟ ولا أستنى وآخر ربع ساعة ده يعدي على خير؟\"",
        "وأخيرًا! الحرية... بس لمدة كام ساعة.":"فيه دكاترة شكلهم جايين من أفلام الرعب... دكتور بكرة واحد منهم."
    },
    {
        "تفتح عينك وتبص على الساعة… وتقول: لسه خمس دقايق.":"أصحى وأفكر: ‘طيب أنا لسه في الثانوية ولا دخلت الجامعة؟’",
        "هو أنا في الكلية ولا في سوق الجمعة؟":"أول كلمة قالها: 'ده مقرر سهل'، وأنا عارف إنها كدبة.",
        "ده المدرج ولا محطة قطار؟ الناس كلها قاعدة ليه كأنهم مستنيين حاجة كبيرة؟":"أبدأ أرتب حاجتي ببطء عشان أطلع أول واحد؟",
        "وأخيرًا! الحرية... بس لمدة كام ساعة.":"اليوم ماشي كأنه فيلم طويل... والجزء التاني لسه جاي بكرة."
    },
    {
        "تفتح عينك وتبص على الساعة… وتقول: لسه خمس دقايق.":"أفتح الموبايل وأشوف النتيجة عشان أتأكد إن فعلاً النهاردة أول يوم دراسي.",
        "هو أنا في الكلية ولا في سوق الجمعة؟":"هو الدكتور ده بيخلص المحاضرة في وقتها ولا بيزود وقت عالراحة؟",
        "ده المدرج ولا محطة قطار؟ الناس كلها قاعدة ليه كأنهم مستنيين حاجة كبيرة؟":"وأول ما تلاقي المحاضرة عدت وفضل فيها ربع ساعة:\"ربع ساعة؟ ده وقت طويل أوي لما تكون مش فاهم حاجة!\"",
        "وأخيرًا! الحرية... بس لمدة كام ساعة.":"خلصت الجامعة، بس الحياة لسه بتضربني."
    },
    {
        "تفتح عينك وتبص على الساعة… وتقول: لسه خمس دقايق.":"أقوم من السرير وأنا بقول لنفسي: ‘إيه اللي خلاني أختار جامعة بعيدة؟’",
        "هو أنا في الكلية ولا في سوق الجمعة؟":"حاسس إني هعيش كابوس المحاضرات مع الدكتور ده.",
        "ده المدرج ولا محطة قطار؟ الناس كلها قاعدة ليه كأنهم مستنيين حاجة كبيرة؟":"وأول ما تلاقي المحاضرة عدت وفضل فيها ربع ساعة:\"أخد نفس عميق وأستعد للجولة الأخيرة.\"",
        "وأخيرًا! الحرية... بس لمدة كام ساعة.":"إزاي اليوم انتهى وأنا لسه مش فاهم إيه اللي حصل فيه؟"
    },
    {
        "تفتح عينك وتبص على الساعة… وتقول: لسه خمس دقايق.":"أصحى، أبص على الساعة وأحسب: لو سبت المحاضرة الأولى وعدّيتها، هل هخلص اليوم أسرع؟",
        "هو أنا في الكلية ولا في سوق الجمعة؟":"أفتح الكشكول ولا أبدأ أفكر في النوم؟",
        "ده المدرج ولا محطة قطار؟ الناس كلها قاعدة ليه كأنهم مستنيين حاجة كبيرة؟":"وأول ما تكتشف إن الدكتور لسه مكمل:\"يا نهار أبيض، هو المحاضرة دي ليها نهاية؟\"",
        "وأخيرًا! الحرية... بس لمدة كام ساعة.":"اليوم ده كأنه فيلم مفيهوش نهاية، بس الأبطال دايمًا تعبانين!"
    },
    {
        "تفتح عينك وتبص على الساعة… وتقول: لسه خمس دقايق.":"أفتح عيني وأول حاجة أفكر فيها: ‘هل ممكن أرجع أنام تاني وخلي اليوم يبدأ من أول وجديد؟’",
        "هو أنا في الكلية ولا في سوق الجمعة؟":"المحاضرة دي مدتها ساعة.. بس حاسس إنها عمر كامل.",
        "ده المدرج ولا محطة قطار؟ الناس كلها قاعدة ليه كأنهم مستنيين حاجة كبيرة؟":"يا ترى لو قمت دلوقتي أعمل نفسي طالع عشان مكالمة هيفتكرني بجد؟",
        "وأخيرًا! الحرية... بس لمدة كام ساعة.":"أنا محتاج أكل يغسل كل الطاقة السلبية اللي جبتها من الجامعة."
    },
    {
        "تفتح عينك وتبص على الساعة… وتقول: لسه خمس دقايق.":"أصحى وأقول: ‘هياحصل إيه لو غبت أول يوم؟ حد هيحس؟’",
        "هو أنا في الكلية ولا في سوق الجمعة؟":"يا ترى هقدر أخرج من هنا بعد المحاضرة ولا هنحبس؟",
        "ده المدرج ولا محطة قطار؟ الناس كلها قاعدة ليه كأنهم مستنيين حاجة كبيرة؟":"هو إحنا في فيلم ولا إيه؟ المفروض خلاصنا!",
        "وأخيرًا! الحرية... بس لمدة كام ساعة.":"هو أنا لو أكلت دلوقتي، هنام في نص الأكلة ولا إيه؟"
    },
    {
        "تفتح عينك وتبص على الساعة… وتقول: لسه خمس دقايق.":"أفتح المنبه وبعدين أكتشف إن التليفون كان على الوضع الصامت طول الليل (ضاع عليك اليوم).",
        "هو أنا في الكلية ولا في سوق الجمعة؟":"محدش قال إن الكلية دي كرف، أنا جاي أتفسح!",
        "ده المدرج ولا محطة قطار؟ الناس كلها قاعدة ليه كأنهم مستنيين حاجة كبيرة؟":"ده أنا بطلت أفكر من ساعة ونص، دلوقتي بعيش على الأمل.",
        "وأخيرًا! الحرية... بس لمدة كام ساعة.":"أطلب دليفري ولا أعمل نفسي طبّاخ وأحرق الأكل؟"
    },
    {
        "تفتح عينك وتبص على الساعة… وتقول: لسه خمس دقايق.":"أصحى وأقول لنفسي: ‘أنا المفروض كنت أبدأ أذاكر من الصيف… أبدأ النهاردة بقى.’",
        "هو أنا في الكلية ولا في سوق الجمعة؟":"الدكتور لسه في المقدمة وأنا حاسس إني مش فاهم حاجة.",
        "ده المدرج ولا محطة قطار؟ الناس كلها قاعدة ليه كأنهم مستنيين حاجة كبيرة؟":"حد يقول للدكتور إن الوقت انتهى، دي معجزة لو خلصنا دلوقتي.",
        "وأخيرًا! الحرية... بس لمدة كام ساعة.":"أول ما أكل، هبدأ أفكر في بكرة... بس بعد ما أخلص بطن دي."
    },
    {
        "تفتح عينك وتبص على الساعة… وتقول: لسه خمس دقايق.":"أول حاجة أعملها، أقوم أجيب الموبايل اللي وقع تحت السرير بعد ما ضربته وهو بيرن.",
        "هو أنا في الكلية ولا في سوق الجمعة؟":"ده امتحان ولا معركة بقاء؟",
        "ده المدرج ولا محطة قطار؟ الناس كلها قاعدة ليه كأنهم مستنيين حاجة كبيرة؟":"لو المحاضرة اتأجلت أو الدكتور ما حضرش:\"يا حلاوة! وقت إضافي للكافيتيريا.\"",
        "وأخيرًا! الحرية... بس لمدة كام ساعة.":"أكلني أي حاجة سريعة قبل ما يجيلي اكتئاب من الجوع والتفكير."
    },
    {
        "تفتح عينك وتبص على الساعة… وتقول: لسه خمس دقايق.":"أقوم وأفكر: ‘إمتى هيطلع قرار إن الجامعة تبدأ الظهر بدل الصبح؟’",
        "هو أنا في الكلية ولا في سوق الجمعة؟":"هو السؤال الأول صعب.. أمال الباقي إيه؟",
        "ده المدرج ولا محطة قطار؟ الناس كلها قاعدة ليه كأنهم مستنيين حاجة كبيرة؟":"لو المحاضرة اتأجلت أو الدكتور ما حضرش:\"أكلم أهلي أقولهم: شوفوا الحظ الجميل ده؟\"",
        "وأخيرًا! الحرية... بس لمدة كام ساعة.":"أول ما تفتكر إن عندك محاضرة بكرة الساعة 8:\"الساعة 8؟! لااااااااا... هو ده امتحان في الصبر؟\""
    },
    {
        "تفتح عينك وتبص على الساعة… وتقول: لسه خمس دقايق.":"أفتح عيني وأحاول أفتكر الحلم اللي كنت فيه… يمكن كان أحلى من الواقع.",
        "هو أنا في الكلية ولا في سوق الجمعة؟":"الامتحان مكتوب بلغة تانية؟ أنا مش فاهم حاجة!",
        "ده المدرج ولا محطة قطار؟ الناس كلها قاعدة ليه كأنهم مستنيين حاجة كبيرة؟":"أول مرة أتمنى الدكتور يكون غايب، وحصل فعلاً!",
        "وأخيرًا! الحرية... بس لمدة كام ساعة.":"أول ما تفتكر إن عندك محاضرة بكرة الساعة 8:\"ليه المحاضرة دي ما بتجيش الساعة 12 كده زي البشر العاديين؟\""
    },
    {
        "تفتح عينك وتبص على الساعة… وتقول: لسه خمس دقايق.":"أقوم من السرير وأقول: ‘مش معقول الصبح جه بسرعة كده… مفيش أي احترام للوقت!’",
        "هو أنا في الكلية ولا في سوق الجمعة؟":"محدش قال إن الأسئلة هتبقى أكتر من عدد صفحات المقرر!",
        "ده المدرج ولا محطة قطار؟ الناس كلها قاعدة ليه كأنهم مستنيين حاجة كبيرة؟":"الغياب ده ممكن يبقى حظ حلو، أو كارثة لما نشوف الجدول الأسبوع الجاي.",
        "وأخيرًا! الحرية... بس لمدة كام ساعة.":"أكيد اللي عمل جدول المحاضرات كان ناوي يخليني أكره الحياة."
    },
    {
        "تفتح عينك وتبص على الساعة… وتقول: لسه خمس دقايق.":"أصحى، أفتح عيني، وأحاول أتفاوض مع نفسي: ‘طب أروح المحاضرة الأولى وبعدين أروح البيت؟’",
        "هو أنا في الكلية ولا في سوق الجمعة؟":"أنا هنجح إزاي وأنا مش فاهم نص الامتحان!",
        "ده المدرج ولا محطة قطار؟ الناس كلها قاعدة ليه كأنهم مستنيين حاجة كبيرة؟":"لو لقيت المدرج كله عمال يضحك:\"هو إحنا بنتفرج على ستاند أب كوميدي ولا إيه؟\"",
        "وأخيرًا! الحرية... بس لمدة كام ساعة.":"أول ما تفتكر إن عندك محاضرة بكرة الساعة 8:\"اللي يحضر محاضرة الساعة 8 بضمير يستحق ميدالية شجاعة.\""
    },
    {
        "تفتح عينك وتبص على الساعة… وتقول: لسه خمس دقايق.":"أفتح المنبه، وبعدها أروح أعمل قهوة وأفضل أبص عليها كأني مستنيها تحل مشاكلي.",
        "هو أنا في الكلية ولا في سوق الجمعة؟":"دخلت الجامعة وأول حاجة فكرت فيها: القهوة فين؟",
        "ده المدرج ولا محطة قطار؟ الناس كلها قاعدة ليه كأنهم مستنيين حاجة كبيرة؟":"يا ترى الناس دي بتضحك عشان فهمت، ولا عشان مش فاهمة زيي؟",
        "وأخيرًا! الحرية... بس لمدة كام ساعة.":"أنا لو حضرت المحاضرة الساعة 8 بكره تاني، مش هفتكر حتى اسمي."
    },
    {
        "تفتح عينك وتبص على الساعة… وتقول: لسه خمس دقايق.":"أصحى وأبص على الحيطان وأقول: ‘إيه الحياة الصعبة دي؟’",
        "هو أنا في الكلية ولا في سوق الجمعة؟":"يا ريتني كنت مكمل على البيت بدل ما أضيع في المتاهة دي.",
        "ده المدرج ولا محطة قطار؟ الناس كلها قاعدة ليه كأنهم مستنيين حاجة كبيرة؟":"لقيت المدرج كله عمال يضحك:\"أنا أضحك معاهم وأعمل نفسي فاهم؟\"",
        "وأخيرًا! الحرية... بس لمدة كام ساعة.":"يا ترى المدرج اللي في آخر الدنيا ده، هفضل أدوّر عليه كام سنة تاني بكره؟"
    },
    {
        "تفتح عينك وتبص على الساعة… وتقول: لسه خمس دقايق.":"أفتح عيني وأحاول أفهم هل أنا صحيت بسبب المنبه ولا الكابوس اللي شفته عن الجامعة؟",
        "هو أنا في الكلية ولا في سوق الجمعة؟":"الجامعة دي شكلها كبير لدرجة إني محتاج GPS!",
        "ده المدرج ولا محطة قطار؟ الناس كلها قاعدة ليه كأنهم مستنيين حاجة كبيرة؟":"الدكتور كان بيقول إيه وأنا سرحت في كلام تاني؟",
        "وأخيرًا! الحرية... بس لمدة كام ساعة.":"مدرج بكرة أكيد متصمم عشان تكره الجامعة أكتر."
    },
    {
        "تفتح عينك وتبص على الساعة… وتقول: لسه خمس دقايق.":"أفتح المنبه وبعدين أفكر: ‘هو لازم أروح الجامعة عشان أتعلم؟ ما الإنترنت موجود!’",
        "هو أنا في الكلية ولا في سوق الجمعة؟":"الدفعة كلها دي، إحنا في جامعة ولا في مول؟",
        "ده المدرج ولا محطة قطار؟ الناس كلها قاعدة ليه كأنهم مستنيين حاجة كبيرة؟":"لو حسيت إن المحاضرة دي ملهاش نهاية:\"هو إحنا هنتخرج ولا هنفضل في المحاضرة دي طول الحياة؟\"",
        "وأخيرًا! الحرية... بس لمدة كام ساعة.":"أفتح الكتاب ولا أفتح يوتيوب وأدور على حاجة تفهمني أسرع؟"
    },
    {
        "تفتح عينك وتبص على الساعة… وتقول: لسه خمس دقايق.":"أصحى، أفتح الستارة وأبص على الشارع… وأفكر: ‘معقول الناس دي صحيت بدري زيي؟’",
        "هو أنا في الكلية ولا في سوق الجمعة؟":"أول خطوة في الجامعة، وآخر خطوة للعقلانية.",
        "ده المدرج ولا محطة قطار؟ الناس كلها قاعدة ليه كأنهم مستنيين حاجة كبيرة؟":"ده الوقت هنا بيعدي بطيء ليه؟ أنا فاكر كنت جاي النهاردة.",
        "وأخيرًا! الحرية... بس لمدة كام ساعة.":"هو فيه أي طريقة أذاكر بيها وأنا نايم؟"
    },
    {
        "تفتح عينك وتبص على الساعة… وتقول: لسه خمس دقايق.":"أقوم وأفتح اللاب توب أشوف مواعيد المحاضرات، وبعدين أكتشف إني فتحت فيسبوك بدلها.",
        "هو أنا في الكلية ولا في سوق الجمعة؟":"ده جدول ولا مسلسل رعب؟",
        "ده المدرج ولا محطة قطار؟ الناس كلها قاعدة ليه كأنهم مستنيين حاجة كبيرة؟":"المدرج ده مصمم عشان تفكر في حياتك وتراجع قراراتك.",
        "وأخيرًا! الحرية... بس لمدة كام ساعة.":"أنا هقعد 10 دقايق أذاكر، وأكيد بعديهم هبدأ في نوبة نوم عميقة."
    },
    {
        "تفتح عينك وتبص على الساعة… وتقول: لسه خمس دقايق.":". \"أول ما أصحى، أبص على الساعة وأقول: ‘طب خمس دقايق كمان، إيه اللي هيحصل؟’\"",
        "هو أنا في الكلية ولا في سوق الجمعة؟":"ليه المحاضرات كلها في الصبح بدري؟ يعني هنتسحر قبل ما نيجي الكلية؟",
        "ده المدرج ولا محطة قطار؟ الناس كلها قاعدة ليه كأنهم مستنيين حاجة كبيرة؟":"يا ترى أنا كده طالب جامعي فعلاً؟ ولا دي مجرد نوبة قلق طويلة؟",
        "وأخيرًا! الحرية... بس لمدة كام ساعة.":"لو المذاكرة كانت رياضة، كنت بقيت بطل أوليمبي في التهرب منها."
    },
    {
        "تفتح عينك وتبص على الساعة… وتقول: لسه خمس دقايق.":". \"أصحى مفزوع وأقول: ‘المحاضرة بدأت! لازم أتحرك!’… وأكتشف إن لسه الساعة 6.\"",
        "هو أنا في الكلية ولا في سوق الجمعة؟":"يوم الجمعة كله نظري؟ يعني حتى الراحة ممنوعة؟",
        "ده المدرج ولا محطة قطار؟ الناس كلها قاعدة ليه كأنهم مستنيين حاجة كبيرة؟":"هو مفيش أمل أخلص المحاضرة وأخرج، ولا لازم أتعود على الوضع ده؟",
        "وأخيرًا! الحرية... بس لمدة كام ساعة.":"وأول ما تبدأ تفكر في اليوم كله:\"اليوم ده مكنش يوم دراسي، ده كان ماراثون ضد الزمن!\""
    },
    {
        "تفتح عينك وتبص على الساعة… وتقول: لسه خمس دقايق.":". \"أقوم وأنا بفكر: ‘هل أول يوم في الجامعة هيكون بنفس الملل اللي كان في المدرسة؟’",
        "هو أنا في الكلية ولا في سوق الجمعة؟":"الجدول ده معمول من خصم اللي متخانق مع الطلبة؟",
        "ده المدرج ولا محطة قطار؟ الناس كلها قاعدة ليه كأنهم مستنيين حاجة كبيرة؟":"وأول ما تدخل المدرج وتكتشف إن مفيش ولا شباك مفتوح:\"ده المدرج ولا السونا؟ هنخرج متبخرين ولا إيه؟\"",
        "وأخيرًا! الحرية... بس لمدة كام ساعة.":"كل حاجة في الجامعة بتعلمني الصبر... حتى البريك اللي مبيجيش."
    },
    {
        "تفتح عينك وتبص على الساعة… وتقول: لسه خمس دقايق.":"أفتح عيني وأقول: ‘مستحيل أكون نايم بس 5 ساعات!’",
        "هو أنا في الكلية ولا في سوق الجمعة؟":"الجدول كأنه تحدي جسدي مش تعليمي، كل محاضرة في قارة.",
        "ده المدرج ولا محطة قطار؟ الناس كلها قاعدة ليه كأنهم مستنيين حاجة كبيرة؟":"اللي قافل الشباك ده عايزنا نموت هنا ولا إيه؟",
        "وأخيرًا! الحرية... بس لمدة كام ساعة.":"أنا عديت اليوم ده، بس اللي جاي أكيد أصعب."
    },
    {
        "تفتح عينك وتبص على الساعة… وتقول: لسه خمس دقايق.":"أفتح عيني وأقول لنفسي: ‘النهاردة اليوم اللي هبدأ أكون فيه شخص جديد’… وبعدها أرجع أنام",
        "هو أنا في الكلية ولا في سوق الجمعة؟":"المدرج ده شكله مكان لجلسات علاج نفسي، مش دراسة.",
        "ده المدرج ولا محطة قطار؟ الناس كلها قاعدة ليه كأنهم مستنيين حاجة كبيرة؟":"أقول للدكتور: ممكن نفتح الشباك عشان التهوية ولا هيفكرني هربان؟",
        "وأخيرًا! الحرية... بس لمدة كام ساعة.":"اليوم ده كان عبارة عن سباق سرعة... وأنا كنت آخر واحد في المضمار."
    },
    {
        "تفتح عينك وتبص على الساعة… وتقول: لسه خمس دقايق.":"أصحى وأبص على السرير وأقول: ‘ليه السرير دا مريح أوي؟’",
        "هو أنا في الكلية ولا في سوق الجمعة؟":"هنا المكان اللي هبقى فيه 4 سنين؟ ده أنا لازم أجيب سرير!",
        "ده المدرج ولا محطة قطار؟ الناس كلها قاعدة ليه كأنهم مستنيين حاجة كبيرة؟":"هو إحنا بندرس ولا بنتمرن في جيم من غير تكييف؟",
        "وأخيرًا! الحرية... بس لمدة كام ساعة.":"أول يوم في الجامعة بيقول لك: 'مرحبًا بك في فيلم الأكشن الواقعي'!"
    },
    {
        "تفتح عينك وتبص على الساعة… وتقول: لسه خمس دقايق.":"أصحى، أفتح التليفون، وأفضل أقلب في التطبيقات عشان أضيع الوقت",
        "هو أنا في الكلية ولا في سوق الجمعة؟":"المدرج ده يجيب النوم، كأنهم مصممينه مخصوص عشان كده.",
        "ده المدرج ولا محطة قطار؟ الناس كلها قاعدة ليه كأنهم مستنيين حاجة كبيرة؟":"أول ما الدكتور يقول: \"اللي فاهم يرفع إيده\":\"أرفع إيدي وأجرب حظي؟ ولا أعمل نفسي مركز؟\"",
        "وأخيرًا! الحرية... بس لمدة كام ساعة.":"أنا مش راجع من الجامعة، أنا راجع من حرب عالمية ثالثة."
    },
    {
        "تفتح عينك وتبص على الساعة… وتقول: لسه خمس دقايق.":"أقوم من السرير وأقول: ‘خليني أرتب السرير… يمكن كده أحس إني نشيط’",
        "هو أنا في الكلية ولا في سوق الجمعة؟":"أنا لو نمت في النص، مين اللي هيصحيني؟",
        "ده المدرج ولا محطة قطار؟ الناس كلها قاعدة ليه كأنهم مستنيين حاجة كبيرة؟":"لو رفعت إيدي هيطلب مني أشرح؟ الله يستر.",
        "وأخيرًا! الحرية... بس لمدة كام ساعة.":"مفروض دلوقتي أقعد وأذاكر؟! لا، أنا محتاج إسعاف الأول."
    },
    {
        "تفتح عينك وتبص على الساعة… وتقول: لسه خمس دقايق.":"أصحى وأفضل أفكر: ‘لو تجاهلت أول يوم… هعرف أعوضه؟’",
        "هو أنا في الكلية ولا في سوق الجمعة؟":"المحاضرة لسه مابدأتش وأنا زهقت من شكله.",
        "ده المدرج ولا محطة قطار؟ الناس كلها قاعدة ليه كأنهم مستنيين حاجة كبيرة؟":"أول ما الدكتور يقول: \"اللي فاهم يرفع إيده\":\"أهو محدش رافع إيده، واضح إننا كلنا في نفس المركب.\"",
        "وأخيرًا! الحرية... بس لمدة كام ساعة.":"حاسس إني شايل هموم العالم على كتافي... وهم المذاكرة على دماغي."
    },
    {
        "تفتح عينك وتبص على الساعة… وتقول: لسه خمس دقايق.":"أفتح المنبه، وبعدين أدور على إيه الحاجة اللي هتخليني أتحرك وأقوم بجد",
        "هو أنا في الكلية ولا في سوق الجمعة؟":"الدكتور شكله جاي يفضّلها بينا، مش يعلّمنا.",
        "ده المدرج ولا محطة قطار؟ الناس كلها قاعدة ليه كأنهم مستنيين حاجة كبيرة؟":"أول ما تكتشف إنك ناسي القلم:\"أكتب بإيه؟ أمسك الهوى وأعمل نفسي بكتب؟\"",
        "وأخيرًا! الحرية... بس لمدة كام ساعة.":"المشي من الجامعة لحد البيت ده لوحده يعتبر تمرين عضلي كامل."
    },
    {
        "تفتح عينك وتبص على الساعة… وتقول: لسه خمس دقايق.":"أصحى، أفكر أعمل رياضة أول اليوم… بس أقرر أبدأ من بكره",
        "هو أنا في الكلية ولا في سوق الجمعة؟":"هو الدكتور ده جاي يعلّم ولا يتشطر علينا؟",
        "ده المدرج ولا محطة قطار؟ الناس كلها قاعدة ليه كأنهم مستنيين حاجة كبيرة؟":"أول ما تكتشف إنك ناسي القلم:\"أسأل اللي جنبي لو عنده قلم ولا هيبص لي بنظرة استحقار؟\"",
        "وأخيرًا! الحرية... بس لمدة كام ساعة.":"الحمد لله وصلت البيت، بس المشكلة إني لازم أرجع تاني بكرة."
    },
    {
        "تفتح عينك وتبص على الساعة… وتقول: لسه خمس دقايق.":"أول ما أصحى، أقعد أعمل حسابات: ‘إمتى ممكن أنام تاني النهاردة؟’",
        "هو أنا في الكلية ولا في سوق الجمعة؟":"أنا هحاول أفهم من نظراته إذا كان بيفكر في إيه.",
        "ده المدرج ولا محطة قطار؟ الناس كلها قاعدة ليه كأنهم مستنيين حاجة كبيرة؟":"هو لازم أكتب دلوقتي؟ ما أنا ممكن أصور المحاضرة كلها.",
        "وأخيرًا! الحرية... بس لمدة كام ساعة.":"هرتاح 10 دقايق... طبعًا العشر دقايق هتبقى ساعتين نوم."
    },
    {
        "تفتح عينك وتبص على الساعة… وتقول: لسه خمس دقايق.":"أصحى وافتكر: ‘أنا ليه اخترت التخصص دا أصلاً؟’",
        "هو أنا في الكلية ولا في سوق الجمعة؟":"الدكتور بتاع محاضرة النهارده ده نوعية اللي ممكن يتكلم ساعتين عشان يقول جملة واحدة.",
        "ده المدرج ولا محطة قطار؟ الناس كلها قاعدة ليه كأنهم مستنيين حاجة كبيرة؟":"لو كنت جايب القلم كان زماني فاهم أكتر",
        "وأخيرًا! الحرية... بس لمدة كام ساعة.":"السرير بيقول لي: تعال، أنت مش هتقوم تاني."
    },
    {
        "تفتح عينك وتبص على الساعة… وتقول: لسه خمس دقايق.":"أصحى وأبص على الساعة وأفضل أحسب: لو قعدت في السرير كمان عشر دقايق هل هخلص كل حاجة في نص ساعة؟",
        "هو أنا في الكلية ولا في سوق الجمعة؟":"هو الدكتور بيشرح ولا بيخترع لغة جديدة؟",
        "ده المدرج ولا محطة قطار؟ الناس كلها قاعدة ليه كأنهم مستنيين حاجة كبيرة؟":"أول ما الدكتور يبدأ يشرح مسألة رياضية:\"هو أنا في حاسبات ولا في هندسة؟ الأرقام دي بتخوف!\"",
        "وأخيرًا! الحرية... بس لمدة كام ساعة.":"هعمل نومة سريعة وبعدين أقوم أذاكر... إزاي النومة السريعة دي بقت غيبوبة 8 ساعات؟"
    },
    {
        "تفتح عينك وتبص على الساعة… وتقول: لسه خمس دقايق.":"أفتح عيني، وأبص على السقف وأقول: ‘إيه اليوم اللي أنا داخله ده؟’",
        "هو أنا في الكلية ولا في سوق الجمعة؟":"السؤال الأول عامل زي اللغز اللي محدش هيعرفه.",
        "ده المدرج ولا محطة قطار؟ الناس كلها قاعدة ليه كأنهم مستنيين حاجة كبيرة؟":"أبدأ أكتب ولا أستنى لحد ما أفهم الأول؟",
        "وأخيرًا! الحرية... بس لمدة كام ساعة.":"لو فتحت كتاب دلوقتي، هيبقى أكتر حاجة رومانسية ممكن أعملها مع نفسي."
    },
    {
        "تفتح عينك وتبص على الساعة… وتقول: لسه خمس دقايق.":"أصحى وأفتكر: ‘نسيت أذاكر… بس هو كده كده أول يوم مش مهم!’",
        "هو أنا في الكلية ولا في سوق الجمعة؟":"الامتحان شكله كأنه معموله تأمين ضد الغش، محدش هيفهمه أصلاً!",
        "ده المدرج ولا محطة قطار؟ الناس كلها قاعدة ليه كأنهم مستنيين حاجة كبيرة؟":"يا ريتني كنت جبت الآلة الحاسبة، كان زماني مركز أكتر.",
        "وأخيرًا! الحرية... بس لمدة كام ساعة.":"هحاول أذاكر وأنا نايم... يمكن العلم يجيلي في الأحلام."
    },
    {
        "تفتح عينك وتبص على الساعة… وتقول: لسه خمس دقايق.":"أول ما أصحى، أبص على الموبايل وأقول: ‘هو أنا ليه مغيرتش نغمة المنبه لحد دلوقتي؟ (بضيع وقت)’",
        "هو أنا في الكلية ولا في سوق الجمعة؟":"أنا مش عارف إذا كان ده امتحان ولا اختبار للذكاء البشري!",
        "ده المدرج ولا محطة قطار؟ الناس كلها قاعدة ليه كأنهم مستنيين حاجة كبيرة؟":"المعادلة دي شكلها أسهل على ورق الشخبطة اللي في البيت.",
        "وأخيرًا! الحرية... بس لمدة كام ساعة.":"المذاكرة مستنية... وأنا بقول لها: بعدين يا حبيبتي."
    },
    {
        "تفتح عينك وتبص على الساعة… وتقول: لسه خمس دقايق.":"أفتح عيني وأقول: ‘هو أنا لسه طالب ولا إيه؟’",
        "هو أنا في الكلية ولا في سوق الجمعة؟":"السؤال ده من المقرر ولا من فيزياء الكواكب؟",
        "ده المدرج ولا محطة قطار؟ الناس كلها قاعدة ليه كأنهم مستنيين حاجة كبيرة؟":"أول ما تلاقي نفسك بتسرح في المحاضرة:\"أركز في اللي بيتقال ولا أكمل أحلام اليقظة؟\"",
        "وأخيرًا! الحرية... بس لمدة كام ساعة.":"الكتاب ده محتاج واحد صاحي يذاكره، وأنا ميت إكلينيكي."
    },
    {
        "تفتح عينك وتبص على الساعة… وتقول: لسه خمس دقايق.":"أول ما أصحى، أقول لنفسي: ‘خلاص، اليوم هيمشي تمام طالما صحيت… أنا واثق!’",
        "هو أنا في الكلية ولا في سوق الجمعة؟":"الوقت بيعدي، وأنا لسه بفكر إذا كنت في الكلية الصح ولا لأ.",
        "ده المدرج ولا محطة قطار؟ الناس كلها قاعدة ليه كأنهم مستنيين حاجة كبيرة؟":"هو أنا جاي أحضر محاضرة ولا أعمل جلسة تأمل؟",
        "وأخيرًا! الحرية... بس لمدة كام ساعة.":"لو فيه مسابقة تهرب من المذاكرة، أكيد هاخد المركز الأول."
    },
    {
        "تفتح عينك وتبص على الساعة… وتقول: لسه خمس دقايق.":"أقوم وأقول: ‘أنا لازم أتعود على الصحوة بدري… معقول مش هبطل الموضوع ده؟’",
        "هو أنا في الكلية ولا في سوق الجمعة؟":"إنت كمان تايه زيي ولا حافظ الطريق؟",
        "ده المدرج ولا محطة قطار؟ الناس كلها قاعدة ليه كأنهم مستنيين حاجة كبيرة؟":"يا ترى الدكتور واخد باله إن نص المدرج سرحان؟",
        "وأخيرًا! الحرية... بس لمدة كام ساعة.":"هفتح الكتاب وبعدين أقلب الصفحة... وأقفل الكتاب وانام."
    },
    {
        "تفتح عينك وتبص على الساعة… وتقول: لسه خمس دقايق.":"أول ما أصحى، أرجع أنام وأقول: ‘أنا أصلًا صاحي بدري ليه؟ مفيش فايدة في المحاضرة الأولى’",
        "هو أنا في الكلية ولا في سوق الجمعة؟":"نقعد نذاكر سوا ولا نهرب من أولها؟",
        "ده المدرج ولا محطة قطار؟ الناس كلها قاعدة ليه كأنهم مستنيين حاجة كبيرة؟":"أعمل نفسي بكتب وأنا في الحقيقة بفكر في الغدا؟",
        "وأخيرًا! الحرية... بس لمدة كام ساعة.":"كل مرة أفكر أذاكر، بكتشف مواهبي في الهروب."
    },
    {
        "تفتح عينك وتبص على الساعة… وتقول: لسه خمس دقايق.":"أصحى وأتأكد إن المنبه صحاني قبل الوقت المحدد… وأفرح إني كسبت خمس دقايق!",
        "هو أنا في الكلية ولا في سوق الجمعة؟":"لو عندك ملخصات، إحنا أصدقاء من دلوقتي.",
        "ده المدرج ولا محطة قطار؟ الناس كلها قاعدة ليه كأنهم مستنيين حاجة كبيرة؟":"المحاضرة دي بتلعب على عقلي ولا أنا اللي من البداية مش متابع؟",
        "وأخيرًا! الحرية... بس لمدة كام ساعة.":"بكرة يوم جديد... بس هو ليه بيبدأ بالجدول ده؟!"
    },
    {
        "تفتح عينك وتبص على الساعة… وتقول: لسه خمس دقايق.":"أول ما أصحى، أفتح الموبايل وأشوف فيه رسائل واتساب… وكأن دي الحاجة الأهم!",
        "هو أنا في الكلية ولا في سوق الجمعة؟":"إيه رأيك نعمل عصابة 'اللي مش فاهمين حاجة'؟",
        "ده المدرج ولا محطة قطار؟ الناس كلها قاعدة ليه كأنهم مستنيين حاجة كبيرة؟":"لما تلاقي المحاضره اللي جايه في كويز :\"اختبار! يا جماعة حد يقولي إزاي الوقت عدّى كده؟\"",
        "وأخيرًا! الحرية... بس لمدة كام ساعة.":"هو أنا لو فضلت نايم، المحاضرات هتتحرك وتجيلي لحد البيت؟"
    },
    {
        "تفتح عينك وتبص على الساعة… وتقول: لسه خمس دقايق.":"أصحى وأفكر: ‘هو في حد أصلاً رايح أول يوم؟’",
        "هو أنا في الكلية ولا في سوق الجمعة؟":"انت أول محاضرة حاسس إنك نجم ولا ضحية؟",
        "ده المدرج ولا محطة قطار؟ الناس كلها قاعدة ليه كأنهم مستنيين حاجة كبيرة؟":"لما تلاقي المحاضره اللي جايه في كويز :\"هو ده تهديد ولا نصيحة؟\"",
        "وأخيرًا! الحرية... بس لمدة كام ساعة.":"بكرة عندي محاضرة 8 الصبح، هو أنا هسهر أذاكر ولا هسهر أتفرج على مسلسلات؟"
    },
    {
        "تفتح عينك وتبص على الساعة… وتقول: لسه خمس دقايق.":"أقوم وأقول: ‘النهاردة أول يوم… يعني لازم أظهر إني ملتزم، بس من بكره هنرجع للنوم!’",
        "هو أنا في الكلية ولا في سوق الجمعة؟":"الناس دي كلها جايين يتعلموا ولا أنا اللي تايه في حفلة مش فاهم فيها حاجة؟",
        "ده المدرج ولا محطة قطار؟ الناس كلها قاعدة ليه كأنهم مستنيين حاجة كبيرة؟":"لما تلاقي المحاضره اللي جايه في كويز :\"الاختبار في إيه بالضبط؟ المحاضرة اللي فاتت ولا حياتنا كلها؟\"",
        "وأخيرًا! الحرية... بس لمدة كام ساعة.":"بكرة أكيد المدرج هيكون أبعد وأصعب... ليه مش بيدونا مكافأة على المشي ده؟"
    },
    {
        "تفتح عينك وتبص على الساعة… وتقول: لسه خمس دقايق.":"أفتح عيني وأتساءل: ‘هو فيه حد بيفكر يروح الجامعة في الوقت ده غيري؟’",
        "هو أنا في الكلية ولا في سوق الجمعة؟":"هو أنا بس اللي حاسس إني لابس هدومي بالعكس؟",
        "ده المدرج ولا محطة قطار؟ الناس كلها قاعدة ليه كأنهم مستنيين حاجة كبيرة؟":"لما تلاقي المحاضره اللي جايه في كويز :\"الدكتور بيقولها كده ببساطة، وأنا قلبي وقع.\"",
        "وأخيرًا! الحرية... بس لمدة كام ساعة.":"المذاكرة دي عاملة زي الرياضة، كل ما تحاول تبدأ، تفتكر إنك مش لابس كوتشي ف تدخل تنام."
    },
    {
        "تفتح عينك وتبص على الساعة… وتقول: لسه خمس دقايق.":"أصحى وأقول: ‘أنا أول مرة أصحى بدري في حياتي… هو أنا فعلاً كبرت؟’",
        "هو أنا في الكلية ولا في سوق الجمعة؟":"يا ريتني كنت نمت بدري، مش فاهم أي حاجة من اللي بيحصل.",
        "ده المدرج ولا محطة قطار؟ الناس كلها قاعدة ليه كأنهم مستنيين حاجة كبيرة؟":"هوا إيه ده! هو فيه وقت نذاكر أصلاً ولا نعتمد على الحظ؟",
        "وأخيرًا! الحرية... بس لمدة كام ساعة.":"هو فيه أي طريقة أحفظ بيها المادة وأنا نايم؟! لازم نطور العلم في الموضوع ده."
    },
    {
        "تفتح عينك وتبص على الساعة… وتقول: لسه خمس دقايق.":"أقوم وأقول لنفسي: ‘أول يوم لازم أظهر فيه بأفضل شكل… بس مفيش وقت!’",
        "هو أنا في الكلية ولا في سوق الجمعة؟":"فين حد ينقذني ويقول لي المدرج فين؟ حسيت إني في فيلم رعب.",
        "ده المدرج ولا محطة قطار؟ الناس كلها قاعدة ليه كأنهم مستنيين حاجة كبيرة؟":"أمشي دلوقتي ولا أستنى وأعمل نفسي ملتزم؟",
        "وأخيرًا! الحرية... بس لمدة كام ساعة.":"المادة دي شكلها عايزة واحد مخه شغال، وأنا للأسف دلوقتي في وضع الطيران."
    },
    {
        "تفتح عينك وتبص على الساعة… وتقول: لسه خمس دقايق.":"أفتح عيني وافتكى: ‘نسيت أجهز حاجتي من الليل!’",
        "هو أنا في الكلية ولا في سوق الجمعة؟":"ليه شكل الكلية دي كأنها متاهة؟ هو إحنا بندرس في مدينة ملاهي؟",
        "ده المدرج ولا محطة قطار؟ الناس كلها قاعدة ليه كأنهم مستنيين حاجة كبيرة؟":"هو فيه باب خلفي أقدر أهرب منه؟",
        "وأخيرًا! الحرية... بس لمدة كام ساعة.":"يا ترى لو أجلت المذاكرة للصبح هعرف أركز أكتر؟ أكيد لا... بس هجرب."
    },
    {
        "تفتح عينك وتبص على الساعة… وتقول: لسه خمس دقايق.":"أقوم من السرير وأقول: ‘لو فضلت نايم، هل حد هيلاحظ إن غيابي مش مهم؟’",
        "هو أنا في الكلية ولا في سوق الجمعة؟":"الجامعة دي شكلها محتاجة خريطة! مشوار كل يوم زي رحلة في الصحراء.",
        "ده المدرج ولا محطة قطار؟ الناس كلها قاعدة ليه كأنهم مستنيين حاجة كبيرة؟":"لو مشيت، هيتحسبلي غياب ولا هكون بطل خارق؟",
        "وأخيرًا! الحرية... بس لمدة كام ساعة.":"المذاكرة بالنسبة لي زي فيلم أكشن طويل، مليان لحظات من الرعب والدراما وانا عايز انام."
    },
    {
        "تفتح عينك وتبص على الساعة… وتقول: لسه خمس دقايق.":"أصحى وأبص على الساعة… وأكتشف إن المنبه كان رن من ساعة وأنا لسه نايم",
        "هو أنا في الكلية ولا في سوق الجمعة؟":"هو المدرج ده مصمم عشان يبقى مدرج نوم ولا مدرج علم؟",
        "ده المدرج ولا محطة قطار؟ الناس كلها قاعدة ليه كأنهم مستنيين حاجة كبيرة؟":"أول خطوة للخروج ممكن تكون فخ، أستنى وأشوف مين هيتجرأ؟",
        "وأخيرًا! الحرية... بس لمدة كام ساعة.":"بكرة يوم جديد... يعني يوم مليان تحديات جديدة ونفس التعب القديم."
    },
    {
        "تفتح عينك وتبص على الساعة… وتقول: لسه خمس دقايق.":"أول ما أصحى، أفتح الموبايل وأشوف ميمز عن أول يوم جامعة، وأفضل أضحك لحد ما أتأخر",
        "هو أنا في الكلية ولا في سوق الجمعة؟":"أول ما سمعت صوت الدكتور: يا ريتني ما كنت سبت السماعات في البيت.",
        "ده المدرج ولا محطة قطار؟ الناس كلها قاعدة ليه كأنهم مستنيين حاجة كبيرة؟":"لو فضلت قاعد هعرف أركز؟ ولا هعيش كده في حالة هروب دائم؟",
        "وأخيرًا! الحرية... بس لمدة كام ساعة.":"بكرة هبقى أحسن، أو هبقى تعبان أكتر... مفيش حل وسط."
    },
    {
        "تفتح عينك وتبص على الساعة… وتقول: لسه خمس دقايق.":"أقوم وأفكر: ‘إيه الحاجة اللي ممكن تخليني فعلاً أروح؟’",
        "هو أنا في الكلية ولا في سوق الجمعة؟":"الدكتور بيشرح بلهجة جديدة؟ ولا أنا بس اللي مش فاهم اللغة؟",
        "ده المدرج ولا محطة قطار؟ الناس كلها قاعدة ليه كأنهم مستنيين حاجة كبيرة؟":"يا نهار! ده المدرج ولا فرح شعبي؟",
        "وأخيرًا! الحرية... بس لمدة كام ساعة.":"بكرة ممكن أبدأ صفحة جديدة مع الجامعة... أو نفس الورقة القديمة بتاعت التهرب."
    },
    {
        "تفتح عينك وتبص على الساعة… وتقول: لسه خمس دقايق.":"أفتح عيني وأفكر في مخرج للهروب من أول يوم دراسي",
        "هو أنا في الكلية ولا في سوق الجمعة؟":"أنا هحاول أعمل نفسي مهتم، بس الحقيقة دماغي بتقول لي 'أنام دلوقتي ولا بعدين؟'",
        "ده المدرج ولا محطة قطار؟ الناس كلها قاعدة ليه كأنهم مستنيين حاجة كبيرة؟":"طب مفيش كراسي فاضية؟ هو أنا هحضر واقف ولا إيه؟",
        "وأخيرًا! الحرية... بس لمدة كام ساعة.":"كل ما أفكر في بكرة، بحس إني في سباق مع الزمن... بس دايمًا الزمن هو اللي بيكسب."
    },
    {
        "تفتح عينك وتبص على الساعة… وتقول: لسه خمس دقايق.":"أصحى وأقول: ‘هو أنا في سنة كام أصلاً؟’",
        "هو أنا في الكلية ولا في سوق الجمعة؟":"هو إحنا هنمتحن من الكلام ده؟ ولا كله كلام في الهوا؟",
        "ده المدرج ولا محطة قطار؟ الناس كلها قاعدة ليه كأنهم مستنيين حاجة كبيرة؟":"لو قعدت على الأرض هتحسبلي حضور؟",
        "وأخيرًا! الحرية... بس لمدة كام ساعة.":"الحمد لله عدى اليوم، بس بكرة أكيد هيكون فيه نفس الدوشة ونفس الزحمة."
    },
    {
        "تفتح عينك وتبص على الساعة… وتقول: لسه خمس دقايق.":"أفتح عيني وأقول: ‘أنا أصلاً مش متأكد أنا في جامعة ولا حلم’",
        "هو أنا في الكلية ولا في سوق الجمعة؟":"المحاضرة لسه مابدأتش وأنا بقيت أحس إني في زنزانة، أنا محبوس هنا؟",
        "ده المدرج ولا محطة قطار؟ الناس كلها قاعدة ليه كأنهم مستنيين حاجة كبيرة؟":"اللي جاب التختة قدام كان جاي من الفجر ولا إيه؟",
        "وأخيرًا! الحرية... بس لمدة كام ساعة.":"حاسس إني شاركت في ماراثون بس بدون جايزة في الآخر."
    },
    {
        "تفتح عينك وتبص على الساعة… وتقول: لسه خمس دقايق.":"أقوم وأنا بفكر: ‘طيب لو كلمت الدكتور وقلت له إني تعبان، هل هيصدق؟’",
        "هو أنا في الكلية ولا في سوق الجمعة؟":"أخيرًا مكان الأمان... الكافتيريا.",
        "ده المدرج ولا محطة قطار؟ الناس كلها قاعدة ليه كأنهم مستنيين حاجة كبيرة؟":"شكلي هقضي المحاضرة وأنا بدور على كرسي زي لعبة الكراسي الموسيقية اهاقهاقهاق.",
        "وأخيرًا! الحرية... بس لمدة كام ساعة.":"أنا مش داخل البيت، أنا داخل العناية المركزة."
    },
    {
        "تفتح عينك وتبص على الساعة… وتقول: لسه خمس دقايق.":"أول ما أصحى، أقول لنفسي: ‘المفروض أكون مجهز نفسي من مبارح… بس هو أول يوم مش محتاج تجهيز!’",
        "هو أنا في الكلية ولا في سوق الجمعة؟":"هو الكافتيريا دي فيها ملخصات؟ لأنها أكيد أهم من المحاضرات.",
        "ده المدرج ولا محطة قطار؟ الناس كلها قاعدة ليه كأنهم مستنيين حاجة كبيرة؟":"وأول ما تلاقي الكرسي اللي قعدت عليه مكسر:\"الحمد لله، المحاضرة هتبقى أكشن.\"",
        "وأخيرًا! الحرية... بس لمدة كام ساعة.":"ياريت في حد يستقبلني بكرسي متحرك دلوقتي."
    },
    {
        "تفتح عينك وتبص على الساعة… وتقول: لسه خمس دقايق.":"أفتح عيني وأقول: ‘هو لازم أول يوم يكون في الصبح؟ مفيش حاجة بعد الظهر؟’",
        "هو أنا في الكلية ولا في سوق الجمعة؟":"كل ما أدخل الجامعة، أول حاجة بفكر فيها: أجيب ساندويتش ولا مشروب طاقة؟",
        "ده المدرج ولا محطة قطار؟ الناس كلها قاعدة ليه كأنهم مستنيين حاجة كبيرة؟":"وأول ما تلاقي الكرسي اللي قعدت عليه مكسر:\"هقعد ثابت ولا الكرسي هيروح بي في رحلة مغامرة؟\"",
        "وأخيرًا! الحرية... بس لمدة كام ساعة.":"يا ترى لو نمت دلوقتي، هل هقدر أصحى قبل ما يخلص الترم؟"
    },
    {
        "تفتح عينك وتبص على الساعة… وتقول: لسه خمس دقايق.":"أصحى وأفكر: ‘طب لو ما رحتش الجامعة النهارده… هل هيحصل حاجة كارثية؟’",
        "هو أنا في الكلية ولا في سوق الجمعة؟":"الكافتيريا هي المكان اللي هتعلم فيه أكتر من المدرج.",
        "ده المدرج ولا محطة قطار؟ الناس كلها قاعدة ليه كأنهم مستنيين حاجة كبيرة؟":"وأول ما تلاقي الكرسي اللي قعدت عليه مكسر:\"لو وقعت، هقول لهم إيه؟ 'آسف يا جماعة، الكرسي هو اللي غدر!'\"",
        "وأخيرًا! الحرية... بس لمدة كام ساعة.":"كل خطوة دلوقتي بتحسبلي زي تدريب في الجيم، بس بدون عضلات."
    },
    {
        "تفتح عينك وتبص على الساعة… وتقول: لسه خمس دقايق.":"أول ما أصحى، أقول: ‘خلاص، دي آخر مرة بصحى بدري… من بكره هبقى بنام أكتر’",
        "هو أنا في الكلية ولا في سوق الجمعة؟":"أول ما وصلت الكافتيريا حسيت إني حققت إنجاز عالمي.",
        "ده المدرج ولا محطة قطار؟ الناس كلها قاعدة ليه كأنهم مستنيين حاجة كبيرة؟":"وأول ما تلاقي الكرسي اللي قعدت عليه مكسر:\"أه... شكلي هبقى التريند بتاع اليوم.\"",
        "وأخيرًا! الحرية... بس لمدة كام ساعة.":"ده السرير ده أعظم اكتشاف في تاريخ البشرية."
    },
    {
        "تفتح عينك وتبص على الساعة… وتقول: لسه خمس دقايق.":"أفتح عيني وأقول: ‘إيه اليوم الصعب ده! هل ممكن أرجع أعيش أيام الإجازة؟’",
        "هو أنا في الكلية ولا في سوق الجمعة؟":"وأول ما تشوف ناس بتهرب من المحاضرات:\"أحسن ناس، عارفين الصح من أولها.\"",
        "ده المدرج ولا محطة قطار؟ الناس كلها قاعدة ليه كأنهم مستنيين حاجة كبيرة؟":"لو الكرسي اتكسر بيا فعلاً، هعتبرها بداية موفقة لسنة أولى جامعة!",
        "وأخيرًا! الحرية... بس لمدة كام ساعة.":"إيه اللي جابني الجامعة وأنا كان ممكن أعيش هنا وأذاكر من على السرير؟"
    },
    {
        "تفتح عينك وتبص على الساعة… وتقول: لسه خمس دقايق.":"أصحى وأفكر: ‘النهاردة لازم أكون جاد… من بكره نبدأ نرجع للروتين’",
        "هو أنا في الكلية ولا في سوق الجمعة؟":"وأول ما تشوف ناس بتهرب من المحاضرات:\"هو الجري ده جزء من الرياضة ولا طقوس الجامعة؟\"",
        "ده المدرج ولا محطة قطار؟ الناس كلها قاعدة ليه كأنهم مستنيين حاجة كبيرة؟":"وأول ما الدكتور يقول: \"افتحوا الكتاب على صفحة 50\":\"يا نهار أبيض، ده أنا حتى مش عارف الكتاب شكله إيه!\"",
        "وأخيرًا! الحرية... بس لمدة كام ساعة.":"أنا محتاج شاحن لنفسي، الطاقة خلصت خلاص."
    },
    {
        "تفتح عينك وتبص على الساعة… وتقول: لسه خمس دقايق.":"أفتح المنبه وبعدين أرجع أنام وأنا بقول: ‘مش هتفرق أول يوم اتأخر شوية’",
        "هو أنا في الكلية ولا في سوق الجمعة؟":"وأول ما تشوف ناس بتهرب من المحاضرات:\"يا ريتني كنت اتعلمت الهروب من زمان.\"",
        "ده المدرج ولا محطة قطار؟ الناس كلها قاعدة ليه كأنهم مستنيين حاجة كبيرة؟":"هي دي محاضره ولا عقوبة؟",
        "وأخيرًا! الحرية... بس لمدة كام ساعة.":"هقوم من السرير دلوقتي... بس خليني أعمل شحن سريع لمدة 5 ساعات."
    },
    {
        "تفتح عينك وتبص على الساعة… وتقول: لسه خمس دقايق.":"أفتح عيني وأقول: ‘هو النهاردة مهم ولا لا؟’",
        "هو أنا في الكلية ولا في سوق الجمعة؟":"أنا مش عارف إذا كان ده يوم دراسي ولا سباق ماراثون للهروب.",
        "ده المدرج ولا محطة قطار؟ الناس كلها قاعدة ليه كأنهم مستنيين حاجة كبيرة؟":"لو فضلت ساكت مش هيحصل حاجة، بس لو نمت هيبقى عيب؟",
        "وأخيرًا! الحرية... بس لمدة كام ساعة.":"السرير بيقول لي: تعال ارتاح، وبكرة كله يتأجل."
    },
    {
        "تفتح عينك وتبص على الساعة… وتقول: لسه خمس دقايق.":"أصحى وأبص على الساعة وأحاول أفهم إذا كان الصبح ولا لسه بليل",
        "هو أنا في الكلية ولا في سوق الجمعة؟":"اللي بيهربوا من المحاضرات دول أساطير المستقبل.",
        "ده المدرج ولا محطة قطار؟ الناس كلها قاعدة ليه كأنهم مستنيين حاجة كبيرة؟":"الدكتور بيشرح معادلة نووية ولا أنا اللي مش مركز؟",
        "وأخيرًا! الحرية... بس لمدة كام ساعة.":"المذاكرة دي مش للشخص اللي أنا عليه دلوقتي... المذاكرة لواحد عنده طاقة."
    },
    {
        "تفتح عينك وتبص على الساعة… وتقول: لسه خمس دقايق.":"أقوم وأقول: ‘مش هتفرق لو نمت عشر دقايق كمان… المنبه دايمًا بيكذب!’",
        "هو أنا في الكلية ولا في سوق الجمعة؟":"وأول ما تشوف الجدول اول ما تتأكد إنه \"حكم مؤبد\":",
        "ده المدرج ولا محطة قطار؟ الناس كلها قاعدة ليه كأنهم مستنيين حاجة كبيرة؟":"يا ترى لو خرجت دلوقتي، حد هيلاحظ؟ ولا أنا أصلاً شفاف؟",
        "وأخيرًا! الحرية... بس لمدة كام ساعة.":"الكتاب ده تحفة فنية، بس مش هقدر أفتحه النهاردة."
    },
    {
        "تفتح عينك وتبص على الساعة… وتقول: لسه خمس دقايق.":"أفتح المنبه وأقول: ‘لو رحت متأخر، يمكن المحاضرة تخلص أسرع؟’",
        "هو أنا في الكلية ولا في سوق الجمعة؟":"الجدول ده معموله لعنة ولا إيه؟",
        "ده المدرج ولا محطة قطار؟ الناس كلها قاعدة ليه كأنهم مستنيين حاجة كبيرة؟":"أول ما تشوف الجدول \"يا لهوي! فين يوم الراحة؟\"",
        "وأخيرًا! الحرية... بس لمدة كام ساعة.":"لو المذاكرة دي كانت زي الأفلام، كان زماني بتفرج وأنا مستمتع."
    },
    {
        "تفتح عينك وتبص على الساعة… وتقول: لسه خمس دقايق.":"أصحى وأقول لنفسي: ‘أول يوم لازم أعمل فيه انطباع… بس شكل الانطباع هيكون إني متأخر’",
        "هو أنا في الكلية ولا في سوق الجمعة؟":"هو فيه حد درس جدول زي ده وخرج سليم؟",
        "ده المدرج ولا محطة قطار؟ الناس كلها قاعدة ليه كأنهم مستنيين حاجة كبيرة؟":"أول ما تشوف الجدول\"الجمعة والسبت كمان دراسة؟ هو أنا وقعت في مؤامرة؟\"",
        "وأخيرًا! الحرية... بس لمدة كام ساعة.":"المخ بيقولي: نام، والواجب بيقول: أنا لسه مستنيك."
    },
    {
        "تفتح عينك وتبص على الساعة… وتقول: لسه خمس دقايق.":"أفتح عيني وأقول: ‘لسه فيه فرصة أهرب من اليوم ده كله؟’",
        "هو أنا في الكلية ولا في سوق الجمعة؟":"يوم السبت كله محاضرات، يعني يوم الراحة اتلغى رسمي؟",
        "ده المدرج ولا محطة قطار؟ الناس كلها قاعدة ليه كأنهم مستنيين حاجة كبيرة؟":"الجدول ده محتاج بطل خارق، مش طالب عادي.",
        "وأخيرًا! الحرية... بس لمدة كام ساعة.":"كل ما أفكر أذاكر، بحس إن مخي بيعمل ريستارت تلقائي."
    },
    {
        "تفتح عينك وتبص على الساعة… وتقول: لسه خمس دقايق.":null,
        "هو أنا في الكلية ولا في سوق الجمعة؟":"الجدول مليان مواد بس مفيش أي وقت للراحة، إيه ده يا عم؟",
        "ده المدرج ولا محطة قطار؟ الناس كلها قاعدة ليه كأنهم مستنيين حاجة كبيرة؟":"أول ما تشوف الجدول\"هو أنا هعيش في الجامعة بقى ولا إيه؟\"",
        "وأخيرًا! الحرية... بس لمدة كام ساعة.":"بكرة هصحى بدري وأكون ملتزم... أو ممكن أديها نوم."
    },
    {
        "تفتح عينك وتبص على الساعة… وتقول: لسه خمس دقايق.":null,
        "هو أنا في الكلية ولا في سوق الجمعة؟":"أعمل نفسي مش واخد بالي من الجدول، يمكن يتغير من غير ما حد يقول لي.",
        "ده المدرج ولا محطة قطار؟ الناس كلها قاعدة ليه كأنهم مستنيين حاجة كبيرة؟":"أول ما تشوف الجدول\"محاضره الساعة 8 صباحًا؟ ده العقاب بتاع إيه بالضبط؟\"",
        "وأخيرًا! الحرية... بس لمدة كام ساعة.":"يا ترى لو ما روحتش بكرة، حد هيلاحظ إني غايب؟"
    },
    {
        "تفتح عينك وتبص على الساعة… وتقول: لسه خمس دقايق.":null,
        "هو أنا في الكلية ولا في سوق الجمعة؟":"ده إحنا بندرس فعلاً؟ مش مجرد نتمشى في الحرم الجامعي؟",
        "ده المدرج ولا محطة قطار؟ الناس كلها قاعدة ليه كأنهم مستنيين حاجة كبيرة؟":"أول ما تشوف الدكتور داخل المدرج متأخر:\"أها، الدكتور برضه بيجي متأخر! مش أنا لوحدي.\"",
        "وأخيرًا! الحرية... بس لمدة كام ساعة.":"بكرة عندي محاضرة الساعة 8... ليه بيحبوا يعذبونا؟"
    },
    {
        "تفتح عينك وتبص على الساعة… وتقول: لسه خمس دقايق.":null,
        "هو أنا في الكلية ولا في سوق الجمعة؟":"أعمل نفسي بأدور على كتاب، بس الحقيقة أنا بدور على مكان أنام فيه.",
        "ده المدرج ولا محطة قطار؟ الناس كلها قاعدة ليه كأنهم مستنيين حاجة كبيرة؟":"هو الدكتور كان بيحضر كورة الصبح ولا إيه؟",
        "وأخيرًا! الحرية... بس لمدة كام ساعة.":"فكرة إني أرجع الجامعة فكرة مرعبة أكتر من فكرة امتحان بكرة."
    }
]